setup.py
DangQu/OCR.py
DangQu/__init__.py
DangQu/click_select.py
DangQu/click_select_picture.py
DangQu/client.py
DangQu/excel_read.py
DangQu/slider.py
DangQu.egg-info/PKG-INFO
DangQu.egg-info/SOURCES.txt
DangQu.egg-info/dependency_links.txt
DangQu.egg-info/requires.txt
DangQu.egg-info/top_level.txt