Metadata-Version: 2.1
Name: DangQu
Version: 0.1.7
Summary: dangqu sdk
Author: DMJ-11740
Author-email: rpa@lumi.com
Classifier: Development Status :: 3 - Alpha
Classifier: Intended Audience :: Developers
Classifier: License :: OSI Approved :: MIT License
Classifier: Programming Language :: Python :: 3
Classifier: Programming Language :: Python :: 3.7
Classifier: Programming Language :: Python :: 3.8
Classifier: Programming Language :: Python :: 3.9
Classifier: Programming Language :: Python :: 3.10
Classifier: Programming Language :: Python :: 3.11
Classifier: Programming Language :: Python :: 3.12
Requires-Dist: requests
Requires-Dist: oauthlib
Requires-Dist: requests-oauthlib
Requires-Dist: pillow
Requires-Dist: numpy
Requires-Dist: ddddocr
Requires-Dist: pandas
Requires-Dist: scipy
Requires-Dist: opencv-python
